README.md
setup.py
plugin_client/FunctionManager.py
plugin_client/__init__.py
plugin_client.egg-info/PKG-INFO
plugin_client.egg-info/SOURCES.txt
plugin_client.egg-info/dependency_links.txt
plugin_client.egg-info/requires.txt
plugin_client.egg-info/top_level.txt