Metadata-Version: 2.1
Name: plugin-client
Version: 0.1.2
Summary: Description of my package
Home-page: 
Author: Luzhipeng
Author-email: 402087139@qq.com
